fastapi_msgspec_openapi/__init__.py
fastapi_msgspec_openapi/plugin.py
fastapi_msgspec_openapi/scanner.py
fastapi_msgspec_openapi/schema.py
fastapi_msgspec_openapi/updater.py
fastapi_msgspec_openapi-0.1.2.dist-info/METADATA
fastapi_msgspec_openapi-0.1.2.dist-info/WHEEL
fastapi_msgspec_openapi-0.1.2.dist-info/licenses/LICENSE
fastapi_msgspec_openapi-0.1.2.dist-info/RECORD
