Metadata-Version: 2.4
Name: fastapi-msgspec-openapi
Version: 0.1.2
Summary: FastAPI plugin for automatic OpenAPI schema generation from msgspec structs
Project-URL: Homepage, https://github.com/S3wnkin/fastapi-msgspec-openapi
Project-URL: Documentation, https://github.com/S3wnkin/fastapi-msgspec-openapi#readme
Project-URL: Repository, https://github.com/S3wnkin/fastapi-msgspec-openapi
Project-URL: Issues, https://github.com/S3wnkin/fastapi-msgspec-openapi/issues
Author-email: RamsesDev <nullint95@gmail.com>
License: MIT
License-File: LICENSE
Keywords: api,documentation,fastapi,msgspec,openapi,serialization,swagger,typescript,validation
Classifier: Development Status :: 3 - Alpha
Classifier: Framework :: FastAPI
Classifier: Intended Audience :: Developers
Classifier: License :: OSI Approved :: MIT License
Classifier: Programming Language :: Python :: 3
Classifier: Programming Language :: Python :: 3.10
Classifier: Programming Language :: Python :: 3.11
Classifier: Programming Language :: Python :: 3.12
Classifier: Programming Language :: Python :: 3.13
Classifier: Topic :: Internet :: WWW/HTTP :: HTTP Servers
Classifier: Topic :: Software Development :: Libraries :: Python Modules
Classifier: Typing :: Typed
Requires-Python: >=3.10
Requires-Dist: fastapi>=0.100.0
Requires-Dist: msgspec>=0.18.0
Provides-Extra: dev
Requires-Dist: httpx>=0.24.0; extra == 'dev'
Requires-Dist: pytest-asyncio>=0.21.0; extra == 'dev'
Requires-Dist: pytest>=7.4.0; extra == 'dev'
